pi3d/Buffer.py
pi3d/Camera.py
pi3d/Display.py
pi3d/Keyboard.py
pi3d/Light.py
pi3d/Mouse.py
pi3d/Shader.py
pi3d/Shape.py
pi3d/Texture.py
pi3d/__init__.py
pi3d/constants/__init__.py
pi3d/constants/egl.py
pi3d/constants/gl.py
pi3d/constants/gl2.py
pi3d/constants/gl2ext.py
pi3d/constants/glext.py
pi3d/event/AbsAxisScaling.py
pi3d/event/Constants.py
pi3d/event/Event.py
pi3d/event/EventHandler.py
pi3d/event/EventStream.py
pi3d/event/EventStruct.py
pi3d/event/FindDevices.py
pi3d/event/Format.py
pi3d/event/Keys.py
pi3d/event/Test.py
pi3d/event/__init__.py
pi3d/event/ioctl.py
pi3d/loader/__init__.py
pi3d/loader/loaderEgg.py
pi3d/loader/loaderObj.py
pi3d/loader/parse_mtl.py
pi3d/loader/parse_mtl_test.py
pi3d/shaders/2d_flat.fs
pi3d/shaders/2d_flat.vs
pi3d/shaders/clashtest.fs
pi3d/shaders/clashtest.vs
pi3d/shaders/conway.fs
pi3d/shaders/conway.vs
pi3d/shaders/defocus.fs
pi3d/shaders/defocus.vs
pi3d/shaders/mat_bump.fs
pi3d/shaders/mat_bump.vs
pi3d/shaders/mat_flat.fs
pi3d/shaders/mat_flat.vs
pi3d/shaders/mat_light.fs
pi3d/shaders/mat_light.vs
pi3d/shaders/mat_pointsprite.fs
pi3d/shaders/mat_pointsprite.vs
pi3d/shaders/mat_reflect.fs
pi3d/shaders/mat_reflect.vs
pi3d/shaders/post_base.fs
pi3d/shaders/post_base.vs
pi3d/shaders/shadow_uv_bump.fs
pi3d/shaders/shadow_uv_bump.vs
pi3d/shaders/shadowcast.fs
pi3d/shaders/shadowcast.vs
pi3d/shaders/star.fs
pi3d/shaders/star.vs
pi3d/shaders/std_bump.inc
pi3d/shaders/std_fog_start.inc
pi3d/shaders/std_head_fs.inc
pi3d/shaders/std_head_vs.inc
pi3d/shaders/std_light.inc
pi3d/shaders/std_main_mat.inc
pi3d/shaders/std_main_uv.inc
pi3d/shaders/std_main_vs.inc
pi3d/shaders/std_shine.inc
pi3d/shaders/uv_bump.fs
pi3d/shaders/uv_bump.vs
pi3d/shaders/uv_elev_map.fs
pi3d/shaders/uv_elev_map.vs
pi3d/shaders/uv_flat.fs
pi3d/shaders/uv_flat.vs
pi3d/shaders/uv_light.fs
pi3d/shaders/uv_light.vs
pi3d/shaders/uv_pointsprite.fs
pi3d/shaders/uv_pointsprite.vs
pi3d/shaders/uv_reflect.fs
pi3d/shaders/uv_reflect.vs
pi3d/shaders/uv_toon.fs
pi3d-2.55.dist-info/licenses/LICENSE
pi3d-2.55.dist-info/METADATA
pi3d-2.55.dist-info/WHEEL
pi3d-2.55.dist-info/top_level.txt
pi3d-2.55.dist-info/RECORD
