Metadata-Version: 2.4
Name: pi3d
Version: 2.55
Summary: pi3d OpenGL 3D graphics library
Author: Tim Skillman, Paddy Gaunt, Tom Ritchford
Maintainer: Paddy Gaunt
License-Expression: MIT
Project-URL: Homepage, http://pi3d.github.com/html/index.html
Keywords: OpenGL,3D,raspberry,raspi,graphics,game engine
Classifier: Development Status :: 5 - Production/Stable
Classifier: Programming Language :: Python
Classifier: Programming Language :: Python :: 3
Classifier: Topic :: Multimedia :: Graphics
Requires-Python: >=3.7
License-File: LICENSE
Requires-Dist: Pillow
Requires-Dist: numpy
Requires-Dist: pysdl2
Dynamic: license-file
